{
  "1": {
    "prop_num": 1,
    "prop_name": "BS EN - HE 100 A - BS EN 10365-2017 BSL",
    "source": "STANDARD",
    "shape": 7,
    "D1": 0.1,
    "D2": 0.1,
    "D3": 0.096,
    "T1": 0.008,
    "T2": 0.008,
    "T3": 0.005,
    "B1": 0.1,
    "B2": 0.1,
    "D": 0.096,
    "tw": 0.008,
    "tf1": 0.008,
    "tf2": 0.005,
    "B": 0.1
  },
  "2": {
    "prop_num": 2,
    "prop_name": "BS EN - IPE 100 - BS EN 10365-2017 BSL",
    "source": "STANDARD",
    "shape": 7,
    "D1": 0.055,
    "D2": 0.055,
    "D3": 0.1,
    "T1": 0.0057,
    "T2": 0.0057,
    "T3": 0.0041,
    "B1": 0.055,
    "B2": 0.055,
    "D": 0.1,
    "tw": 0.0057,
    "tf1": 0.0057,
    "tf2": 0.0041,
    "B": 0.055
  }
}